metaai_api/__init__.py
metaai_api/api_server.py
metaai_api/client.py
metaai_api/exceptions.py
metaai_api/image_upload.py
metaai_api/main.py
metaai_api/utils.py
metaai_api/video_generation.py
metaai_sdk-3.0.0.dist-info/licenses/LICENSE
metaai_sdk-3.0.0.dist-info/METADATA
metaai_sdk-3.0.0.dist-info/WHEEL
metaai_sdk-3.0.0.dist-info/top_level.txt
metaai_sdk-3.0.0.dist-info/RECORD
