Metadata-Version: 2.4
Name: metaai-sdk
Version: 3.0.0
Summary: Feature-rich Python SDK for Meta AI - Chat, Image & Video Generation powered by Llama 3
Author-email: Ashiq Hussain Mir <imseldrith@gmail.com>
License-Expression: MIT
Project-URL: Homepage, https://github.com/mir-ashiq/metaai-api
Project-URL: Documentation, https://github.com/mir-ashiq/metaai-api/blob/main/README.md
Project-URL: Repository, https://github.com/mir-ashiq/metaai-api
Project-URL: Changelog, https://github.com/mir-ashiq/metaai-api/blob/main/CHANGELOG.md
Keywords: metaai,meta-ai,llama3,ai,llm,video-generation,chatbot
Classifier: Development Status :: 5 - Production/Stable
Classifier: Intended Audience :: Developers
Classifier: Programming Language :: Python :: 3
Classifier: Programming Language :: Python :: 3.7
Classifier: Programming Language :: Python :: 3.8
Classifier: Programming Language :: Python :: 3.9
Classifier: Programming Language :: Python :: 3.10
Classifier: Programming Language :: Python :: 3.11
Classifier: Programming Language :: Python :: 3.12
Requires-Python: >=3.7
License-File: LICENSE
Requires-Dist: requests>=2.31.0
Requires-Dist: requests-html>=0.10.0
Requires-Dist: lxml-html-clean>=0.1.1
Requires-Dist: beautifulsoup4>=4.9.0
Requires-Dist: python-multipart>=0.0.21
Provides-Extra: api
Requires-Dist: fastapi>=0.95.2; extra == "api"
Requires-Dist: uvicorn[standard]>=0.22.0; extra == "api"
Requires-Dist: python-multipart>=0.0.6; extra == "api"
Requires-Dist: python-dotenv>=1.0.0; extra == "api"
Provides-Extra: dev
Requires-Dist: check-manifest; extra == "dev"
Requires-Dist: pytest; extra == "dev"
Requires-Dist: black; extra == "dev"
Requires-Dist: flake8; extra == "dev"
Dynamic: license-file
